MANIFEST.in
setup.py
paxmusica/__init__.py
paxmusica/__init__.pyc
paxmusica/cli.py
paxmusica/cli.pyc
paxmusica/config.py
paxmusica/config.pyc
paxmusica/controller.py
paxmusica/controller.pyc
paxmusica/model.py
paxmusica/model.pyc
paxmusica/player.py
paxmusica/player.pyc
paxmusica.egg-info/PKG-INFO
paxmusica.egg-info/SOURCES.txt
paxmusica.egg-info/dependency_links.txt
paxmusica.egg-info/entry_points.txt
paxmusica.egg-info/not-zip-safe
paxmusica.egg-info/requires.txt
paxmusica.egg-info/top_level.txt
paxmusica/static/bg.png
paxmusica/static/favicon.png
paxmusica/static/logo.png
paxmusica/static/logo.xcf
paxmusica/static/main.css
paxmusica/static/mobile-main.css
paxmusica/static/my.css
paxmusica/static/my.js
paxmusica/templates/albums.html
paxmusica/templates/index.html
paxmusica/templates/playlist.html
paxmusica/templates/songs.html
paxmusica/templates/update.html
paxmusica/templates/Old/index.html.jinja
paxmusica/templates/Old/mobile/index.html.jinja
paxmusica/templates/Old/mobile/playlist.html.jinja