Metadata-Version: 1.0
Name: paxmusica
Version: 0.0.3
Summary: Peace on Playlists
Home-page: UNKNOWN
Author: Christian Kokoska
Author-email: UNKNOWN
License: UNKNOWN
Platform: UNKNOWN
